{"tokens": ["5.455", "AOUA3TOL", "SUBTOTAL5455", "10.0002", "10", "PH", "546", "AMQUNT", "TOTAL6.001", "CASH6.001"], "bboxes": [[659, 528, 755, 558], [301, 531, 471, 562], [279, 559, 748, 595], [633, 590, 764, 621], [363, 593, 421, 627], [285, 595, 338, 628], [688, 621, 761, 653], [266, 625, 385, 664], [253, 685, 771, 731], [259, 725, 792, 771]], "original_boxes": [[633, 676, 725, 715], [289, 680, 453, 720], [268, 716, 719, 762], [608, 756, 734, 796], [349, 760, 405, 803], [274, 762, 325, 805], [661, 796, 731, 837], [256, 801, 370, 850], [243, 878, 741, 936], [249, 928, 761, 987]], "labels": [[1, "menu.price"], [0, "menu.nm"], [2, "sub_total.subtotal_price"], [4, "sub_total.tax_price"], [3, "other"], [3, "other"], [5, "other"], [6, "other"], [7, "total.total_price"], [8, "total.cashprice"]], "linkings": null, "image_path": "/media/ai2lab/4TB SSD/Datasets/Token-Path-Prediction-Datasets/CORD-r/images/train_0495.png"}