{"tokens": ["Pepenero", "Pastel", "15.000", "1x", "15.000", "SubtotalRp", "15.000", "Tax(10.0%)Rp", "1.500", "TotalRp", "16.500", "CashRp", "50.500", "ChangeRp", "34.000", "0"], "bboxes": [[205, 492, 323, 515], [338, 493, 416, 516], [285, 520, 378, 543], [208, 521, 237, 541], [570, 522, 659, 548], [205, 575, 556, 602], [571, 580, 655, 602], [207, 603, 568, 629], [584, 608, 655, 629], [205, 656, 555, 684], [569, 662, 655, 684], [201, 711, 553, 738], [567, 715, 655, 740], [201, 738, 552, 765], [565, 744, 653, 767], [203, 824, 240, 855]], "original_boxes": [[228, 728, 358, 762], [375, 729, 461, 764], [316, 770, 419, 804], [231, 771, 263, 801], [632, 772, 731, 810], [228, 851, 617, 890], [633, 858, 726, 890], [230, 892, 630, 931], [648, 899, 726, 931], [228, 971, 615, 1012], [631, 979, 726, 1012], [223, 1052, 613, 1091], [629, 1058, 726, 1095], [223, 1091, 612, 1131], [627, 1100, 724, 1135], [225, 1219, 266, 1264]], "labels": [[0, "menu.nm"], [0, "menu.nm"], [2, "menu.unitprice"], [1, "menu.cnt"], [3, "menu.price"], [4, "sub_total.subtotal_price"], [4, "sub_total.subtotal_price"], [5, "sub_total.tax_price"], [5, "sub_total.tax_price"], [6, "total.total_price"], [6, "total.total_price"], [7, "total.cashprice"], [7, "total.cashprice"], [8, "total.changeprice"], [8, "total.changeprice"], [9, "other"]], "linkings": null, "image_path": "/media/ai2lab/4TB SSD/Datasets/Token-Path-Prediction-Datasets/CORD-r/images/train_0026.png"}