{"tokens": ["SBL", "GR", "UDANG", "SPC", "30,000", "1.00", "ITEMS", "GUBTOTAL30,000", "TAX", "10%3,000", "TOTAL33,000", "CASH33,000"], "bboxes": [[168, 456, 225, 483], [250, 457, 288, 484], [312, 458, 413, 487], [437, 460, 500, 489], [697, 461, 831, 494], [390, 493, 475, 523], [498, 494, 598, 525], [157, 524, 831, 561], [149, 556, 220, 590], [244, 557, 836, 599], [145, 592, 838, 635], [140, 630, 840, 672]], "original_boxes": [[97, 394, 130, 418], [144, 395, 166, 419], [180, 396, 238, 421], [252, 398, 288, 423], [402, 399, 479, 427], [225, 426, 274, 452], [287, 427, 345, 454], [91, 453, 479, 485], [86, 481, 127, 510], [141, 482, 482, 518], [84, 512, 483, 549], [81, 545, 484, 581]], "labels": [[0, "menu.nm"], [0, "menu.nm"], [0, "menu.nm"], [0, "menu.nm"], [1, "menu.price"], [2, "total.menuqty_cnt"], [2, "total.menuqty_cnt"], [3, "sub_total.subtotal_price"], [4, "sub_total.tax_price"], [4, "sub_total.tax_price"], [5, "total.total_price"], [6, "total.cashprice"]], "linkings": null, "image_path": "/media/ai2lab/4TB SSD/Datasets/Token-Path-Prediction-Datasets/CORD-r/images/train_0229.png"}