{"tokens": ["AFUNGAFUNGAFUNGAFUNGAFU", "43.636", "1", "43.636", "BIHN", "TAHU", "BASO", "TOTAL43.636", "4.34TAX10.00%", "TOTA48.000", "GRAND", "TUNAI100.000", "KEMBALI52.000"], "bboxes": [[752, 70, 833, 978], [636, 660, 739, 689], [421, 664, 453, 690], [453, 664, 561, 690], [269, 667, 351, 691], [186, 669, 252, 693], [103, 671, 168, 695], [101, 692, 741, 729], [104, 756, 744, 790], [201, 792, 739, 817], [100, 793, 182, 819], [103, 822, 740, 853], [100, 854, 739, 884]], "original_boxes": [[650, 92, 720, 1268], [550, 856, 639, 894], [364, 861, 392, 895], [392, 861, 485, 895], [233, 865, 304, 896], [161, 868, 218, 899], [89, 870, 146, 901], [88, 897, 641, 946], [90, 980, 643, 1025], [174, 1027, 639, 1060], [87, 1029, 158, 1062], [89, 1066, 640, 1106], [87, 1108, 639, 1146]], "labels": [[0, "other"], [3, "menu.price"], [1, "menu.cnt"], [2, "menu.unitprice"], [4, "menu.nm"], [4, "menu.nm"], [4, "menu.nm"], [5, "sub_total.subtotal_price"], [6, "sub_total.tax_price"], [7, "total.total_price"], [7, "total.total_price"], [8, "total.cashprice"], [9, "total.changeprice"]], "linkings": null, "image_path": "/media/ai2lab/4TB SSD/Datasets/Token-Path-Prediction-Datasets/CORD-r/images/train_0046.png"}