{"tokens": ["1", "REDBEAN", "BREAD", "9,000", "1", "KAYA", "BUN", "9,500", "2", "REAL", "MILK", "CHOCO", "BREAD", "25,000", "TOTAL43,500", "CASH50,500", "CHANGE7,000", "L"], "bboxes": [[133, 395, 151, 424], [175, 395, 326, 425], [347, 398, 456, 428], [788, 400, 904, 435], [135, 434, 151, 461], [175, 434, 262, 461], [286, 434, 355, 461], [782, 435, 902, 471], [130, 468, 154, 496], [178, 468, 262, 496], [286, 468, 366, 496], [394, 468, 494, 496], [519, 468, 618, 497], [762, 469, 901, 505], [175, 535, 892, 596], [173, 591, 892, 628], [171, 621, 895, 690], [156, 763, 357, 809]], "original_boxes": [[77, 342, 87, 367], [101, 342, 188, 368], [200, 344, 263, 370], [454, 346, 521, 376], [78, 375, 87, 399], [101, 375, 151, 399], [165, 375, 205, 399], [451, 376, 520, 407], [75, 405, 89, 429], [103, 405, 151, 429], [165, 405, 211, 429], [227, 405, 285, 429], [299, 405, 356, 430], [439, 406, 519, 437], [101, 463, 514, 515], [100, 511, 514, 543], [99, 537, 516, 597], [90, 660, 206, 699]], "labels": [[0, "menu.cnt"], [1, "menu.nm"], [1, "menu.nm"], [2, "menu.price"], [3, "menu.cnt"], [4, "menu.nm"], [4, "menu.nm"], [5, "menu.price"], [6, "menu.cnt"], [7, "menu.nm"], [7, "menu.nm"], [7, "menu.nm"], [7, "menu.nm"], [8, "menu.price"], [9, "total.total_price"], [10, "total.cashprice"], [11, "total.changeprice"], [12, "other"]], "linkings": null, "image_path": "/media/ai2lab/4TB SSD/Datasets/Token-Path-Prediction-Datasets/CORD-r/images/train_0570.png"}