{"tokens": ["1", "CHOCO", "CUSTAFD", "PASTRY", "12,000", "1", "CUSTARD", "BRI", "CHE", "9,000", "21,000TOTAL", "50,000CASH", "29,000CHANGE"], "bboxes": [[238, 433, 261, 454], [276, 432, 355, 453], [372, 431, 485, 451], [503, 429, 601, 449], [735, 427, 842, 449], [240, 457, 262, 478], [273, 456, 387, 476], [402, 455, 454, 475], [469, 454, 522, 475], [746, 449, 842, 473], [273, 494, 842, 538], [275, 533, 842, 559], [271, 556, 843, 602]], "original_boxes": [[550, 1774, 602, 1861], [636, 1773, 818, 1856], [859, 1768, 1119, 1849], [1161, 1761, 1386, 1843], [1694, 1749, 1940, 1843], [554, 1872, 605, 1959], [631, 1871, 893, 1952], [927, 1865, 1048, 1949], [1082, 1861, 1203, 1946], [1720, 1843, 1940, 1941], [631, 2026, 1941, 2206], [635, 2185, 1940, 2291], [625, 2278, 1944, 2468]], "labels": [[1, "menu.cnt"], [2, "menu.nm"], [2, "menu.nm"], [2, "menu.nm"], [0, "menu.price"], [4, "menu.cnt"], [5, "menu.nm"], [5, "menu.nm"], [5, "menu.nm"], [3, "menu.price"], [6, "total.total_price"], [7, "total.cashprice"], [8, "total.changeprice"]], "linkings": null, "image_path": "/media/ai2lab/4TB SSD/Datasets/Token-Path-Prediction-Datasets/CORD-r/images/train_0773.png"}