{"form": [{"box": [885, 363, 1525, 434], "text": "登记资料变更表(3)", "label": "header", "words": [{"text": "登记", "box": [885, 363, 1023, 433]}, {"text": "资料", "box": [1032, 363, 1168, 433]}, {"text": "变更", "box": [1168, 364, 1311, 434]}, {"text": "表", "box": [1314, 364, 1386, 433]}, {"text": "(", "box": [1421, 365, 1447, 434]}, {"text": "3", "box": [1457, 365, 1486, 434]}, {"text": ")", "box": [1502, 365, 1525, 434]}], "linking": [], "id": 0}, {"box": [779, 473, 1660, 514], "text": "(已填写公民登记表者,如情况有变化请填此表)", "label": "other", "words": [{"text": "(", "box": [779, 473, 798, 514]}, {"text": "已", "box": [807, 473, 840, 514]}, {"text": "填写", "box": [846, 473, 927, 514]}, {"text": "公民", "box": [932, 473, 1010, 514]}, {"text": "登记", "box": [1016, 473, 1095, 514]}, {"text": "表", "box": [1101, 473, 1136, 514]}, {"text": "者", "box": [1141, 473, 1175, 514]}, {"text": ",", "box": [1185, 473, 1193, 514]}, {"text": "如", "box": [1224, 473, 1260, 514]}, {"text": "情况", "box": [1267, 473, 1345, 514]}, {"text": "有", "box": [1352, 473, 1386, 514]}, {"text": "变化", "box": [1393, 473, 1470, 514]}, {"text": "请", "box": [1476, 473, 1512, 514]}, {"text": "填", "box": [1518, 473, 1555, 514]}, {"text": "此", "box": [1560, 473, 1595, 514]}, {"text": "表", "box": [1602, 473, 1638, 514]}, {"text": ")", "box": [1647, 473, 1660, 514]}], "linking": [], "id": 1}, {"box": [422, 555, 730, 616], "text": "(原)姓名:", "label": "question", "words": [{"text": "(", "box": [422, 559, 449, 616]}, {"text": "原", "box": [455, 557, 515, 615]}, {"text": ")", "box": [527, 557, 550, 614]}, {"text": "姓名", "box": [584, 556, 703, 614]}, {"text": ":", "box": [719, 555, 730, 612]}], "linking": [[2, 34]], "id": 2}, {"box": [1324, 566, 1671, 616], "text": "原登记表编号:", "label": "question", "words": [{"text": "原", "box": [1324, 566, 1373, 616]}, {"text": "登记", "box": [1377, 566, 1484, 616]}, {"text": "表", "box": [1490, 566, 1540, 616]}, {"text": "编号", "box": [1546, 566, 1650, 616]}, {"text": ":", "box": [1661, 566, 1671, 616]}], "linking": [[3, 35]], "id": 3}, {"box": [415, 662, 741, 715], "text": "变化资料项目", "label": "question", "words": [{"text": "变化", "box": [415, 662, 524, 715]}, {"text": "资料", "box": [532, 662, 637, 715]}, {"text": "项目", "box": [642, 663, 741, 715]}], "linking": [[4, 7], [4, 9], [4, 11], [4, 13], [4, 15], [4, 17], [4, 19], [4, 21], [4, 23], [4, 25], [4, 27], [4, 29], [4, 31]], "id": 4}, {"box": [1085, 662, 1471, 717], "text": "变化后的新资料", "label": "other", "words": [{"text": "变化", "box": [1085, 662, 1191, 717]}, {"text": "后", "box": [1199, 662, 1245, 717]}, {"text": "的", "box": [1257, 662, 1301, 717]}, {"text": "新", "box": [1308, 662, 1361, 717]}, {"text": "资料", "box": [1370, 662, 1471, 717]}], "linking": [], "id": 5}, {"box": [1860, 665, 1968, 716], "text": "备注", "label": "other", "words": [{"text": "备注", "box": [1860, 665, 1968, 716]}], "linking": [], "id": 6}, {"box": [562, 775, 663, 829], "text": "国籍", "label": "question", "words": [{"text": "国籍", "box": [562, 775, 663, 829]}], "linking": [[4, 7], [7, 8]], "id": 7}, {"box": [956, 772, 1141, 814], "text": "哥伦比亚", "label": "answer", "words": [{"text": "哥伦比亚", "box": [956, 772, 1141, 814]}], "linking": [[7, 8]], "id": 8}, {"box": [418, 888, 749, 1015], "text": "姓名(外文或拼音)", "label": "question", "words": [{"text": "姓", "box": [484, 888, 540, 941]}, {"text": "名", "box": [681, 888, 728, 941]}, {"text": "(", "box": [418, 962, 439, 1015]}, {"text": "外文", "box": [448, 962, 555, 1015]}, {"text": "或", "box": [562, 962, 610, 1015]}, {"text": "拼音", "box": [619, 962, 721, 1015]}, {"text": ")", "box": [733, 962, 749, 1015]}], "linking": [[4, 9], [9, 10]], "id": 9}, {"box": [946, 927, 1149, 980], "text": "wangwei", "label": "answer", "words": [{"text": "wang", "box": [946, 932, 1061, 980]}, {"text": "wei", "box": [1072, 927, 1149, 971]}], "linking": [[9, 10]], "id": 10}, {"box": [472, 1074, 692, 1130], "text": "护照号码", "label": "question", "words": [{"text": "护照", "box": [472, 1074, 578, 1129]}, {"text": "号码", "box": [585, 1075, 692, 1130]}], "linking": [[4, 11], [11, 12]], "id": 11}, {"box": [861, 1084, 1095, 1119], "text": "J59416328", "label": "answer", "words": [{"text": "J59416328", "box": [861, 1084, 1095, 1119]}], "linking": [[11, 12]], "id": 12}, {"box": [471, 1227, 688, 1280], "text": "发照机关", "label": "question", "words": [{"text": "发", "box": [471, 1227, 520, 1278]}, {"text": "照", "box": [527, 1227, 576, 1278]}, {"text": "机关", "box": [584, 1227, 688, 1280]}], "linking": [[4, 13], [13, 14]], "id": 13}, {"box": [869, 1221, 1199, 1266], "text": "哥伦比亚共和国", "label": "answer", "words": [{"text": "哥伦比亚", "box": [869, 1221, 1058, 1266]}, {"text": "共和国", "box": [1062, 1221, 1199, 1266]}], "linking": [[13, 14]], "id": 14}, {"box": [440, 1374, 713, 1431], "text": "护照有效期", "label": "question", "words": [{"text": "护照", "box": [440, 1374, 547, 1429]}, {"text": "有效期", "box": [552, 1375, 713, 1431]}], "linking": [[4, 15], [15, 16]], "id": 15}, {"box": [885, 1391, 1324, 1425], "text": "2019.11.01-2020.5.1", "label": "answer", "words": [{"text": "2019.11.01-2020.5.1", "box": [885, 1391, 1324, 1425]}], "linking": [[15, 16]], "id": 16}, {"box": [467, 1491, 685, 1617], "text": "在哥居留签证种类", "label": "question", "words": [{"text": "在", "box": [467, 1491, 518, 1541]}, {"text": "哥", "box": [523, 1491, 575, 1541]}, {"text": "居留", "box": [578, 1492, 684, 1542]}, {"text": "签证", "box": [467, 1564, 574, 1616]}, {"text": "种类", "box": [582, 1564, 685, 1617]}], "linking": [[4, 17], [17, 18]], "id": 17}, {"box": [934, 1532, 1120, 1577], "text": "临时签证", "label": "answer", "words": [{"text": "临时", "box": [934, 1532, 1022, 1576]}, {"text": "签证", "box": [1028, 1532, 1120, 1577]}], "linking": [[17, 18]], "id": 18}, {"box": [437, 1677, 711, 1730], "text": "签证有效期", "label": "question", "words": [{"text": "签证", "box": [437, 1677, 545, 1730]}, {"text": "有效期", "box": [552, 1677, 711, 1730]}], "linking": [[4, 19], [19, 20]], "id": 19}, {"box": [884, 1692, 1352, 1727], "text": "2019.12.01-2020.1.29", "label": "answer", "words": [{"text": "2019.12.01-2020.1.29", "box": [884, 1692, 1352, 1727]}], "linking": [[19, 20]], "id": 20}, {"box": [410, 1828, 738, 1880], "text": "签证颁发地点", "label": "question", "words": [{"text": "签证", "box": [410, 1828, 516, 1880]}, {"text": "颁发", "box": [527, 1828, 630, 1880]}, {"text": "地点", "box": [638, 1828, 738, 1880]}], "linking": [[4, 21], [21, 22]], "id": 21}, {"box": [921, 1836, 1350, 1881], "text": "哥伦比亚驻华大使馆", "label": "answer", "words": [{"text": "哥伦比亚", "box": [921, 1836, 1108, 1881]}, {"text": "驻华", "box": [1113, 1836, 1206, 1881]}, {"text": "大使馆", "box": [1211, 1836, 1350, 1881]}], "linking": [[21, 22]], "id": 22}, {"box": [466, 1978, 683, 2029], "text": "在哥住址", "label": "question", "words": [{"text": "在", "box": [466, 1978, 516, 2027]}, {"text": "哥", "box": [523, 1978, 571, 2027]}, {"text": "住址", "box": [577, 1978, 683, 2029]}], "linking": [[4, 23], [23, 24]], "id": 23}, {"box": [878, 1965, 1207, 2011], "text": "曼哈顿的哈林区", "label": "answer", "words": [{"text": "曼哈顿", "box": [878, 1965, 1018, 2011]}, {"text": "的", "box": [1025, 1965, 1064, 2011]}, {"text": "哈林", "box": [1071, 1965, 1163, 2011]}, {"text": "区", "box": [1167, 1965, 1207, 2011]}], "linking": [[23, 24]], "id": 24}, {"box": [381, 2128, 734, 2235], "text": "住址电话、手机、传真、电邮等", "label": "question", "words": [{"text": "住址", "box": [381, 2128, 476, 2172]}, {"text": "电话", "box": [485, 2128, 572, 2172]}, {"text": "、", "box": [582, 2128, 592, 2172]}, {"text": "手机", "box": [626, 2128, 715, 2172]}, {"text": "、", "box": [725, 2128, 734, 2172]}, {"text": "传真", "box": [430, 2191, 522, 2235]}, {"text": "、", "box": [532, 2191, 542, 2235]}, {"text": "电邮", "box": [582, 2191, 667, 2235]}, {"text": "等", "box": [674, 2191, 713, 2235]}], "linking": [[4, 25], [25, 26]], "id": 25}, {"box": [896, 2173, 1186, 2207], "text": "13689562233", "label": "answer", "words": [{"text": "13689562233", "box": [896, 2173, 1186, 2207]}], "linking": [[25, 26]], "id": 26}, {"box": [435, 2298, 707, 2420], "text": "在哥工作单位、职业", "label": "question", "words": [{"text": "在", "box": [462, 2298, 512, 2349]}, {"text": "哥", "box": [518, 2298, 568, 2349]}, {"text": "工作", "box": [578, 2298, 680, 2349]}, {"text": "单位", "box": [435, 2371, 542, 2420]}, {"text": "、", "box": [554, 2371, 564, 2420]}, {"text": "职业", "box": [605, 2371, 707, 2420]}], "linking": [[4, 27], [27, 28]], "id": 27}, {"box": [927, 2333, 1402, 2380], "text": "哥伦比亚贸易有限公司", "label": "answer", "words": [{"text": "哥伦比亚", "box": [927, 2333, 1117, 2379]}, {"text": "贸易", "box": [1123, 2335, 1211, 2379]}, {"text": "有限公司", "box": [1217, 2334, 1402, 2380]}], "linking": [[27, 28]], "id": 28}, {"box": [437, 2446, 708, 2573], "text": "工作单位电话、传真", "label": "question", "words": [{"text": "工作", "box": [465, 2446, 570, 2497]}, {"text": "单位", "box": [578, 2446, 683, 2497]}, {"text": "电话", "box": [437, 2516, 542, 2571]}, {"text": "、", "box": [552, 2518, 564, 2570]}, {"text": "传真", "box": [604, 2519, 708, 2573]}], "linking": [[4, 29], [29, 30]], "id": 29}, {"box": [914, 2500, 1180, 2533], "text": "5717464544", "label": "answer", "words": [{"text": "5717464544", "box": [914, 2500, 1180, 2533]}], "linking": [[29, 30]], "id": 30}, {"box": [430, 2597, 705, 2722], "text": "国内联系人及联系电话", "label": "question", "words": [{"text": "国内", "box": [436, 2597, 536, 2649]}, {"text": "联系人", "box": [546, 2597, 705, 2650]}, {"text": "及", "box": [430, 2671, 483, 2720]}, {"text": "联系", "box": [489, 2671, 591, 2721]}, {"text": "电话", "box": [608, 2671, 705, 2722]}], "linking": [[4, 31], [31, 32]], "id": 31}, {"box": [876, 2638, 1164, 2674], "text": "18236597788", "label": "answer", "words": [{"text": "18236597788", "box": [876, 2638, 1164, 2674]}], "linking": [[31, 32]], "id": 32}, {"box": [374, 3044, 652, 3106], "text": "填写日期:", "label": "question", "words": [{"text": "填写", "box": [374, 3045, 496, 3106]}, {"text": "日期", "box": [518, 3045, 625, 3105]}, {"text": ":", "box": [640, 3044, 652, 3104]}], "linking": [[33, 37]], "id": 33}, {"box": [767, 554, 859, 612], "text": "王伟", "label": "answer", "words": [{"text": "王伟", "box": [767, 554, 859, 612]}], "linking": [[2, 34]], "id": 34}, {"box": [1716, 566, 1840, 616], "text": "10032", "label": "answer", "words": [{"text": "10032", "box": [1716, 566, 1840, 616]}], "linking": [[3, 35]], "id": 35}, {"box": [470, 2782, 666, 2838], "text": "其他", "label": "other", "words": [{"text": "其他", "box": [470, 2782, 666, 2838]}], "linking": [], "id": 36}, {"box": [749, 3027, 1153, 3106], "text": "2019年1016", "label": "answer", "words": [{"text": "2019", "box": [749, 3027, 861, 3098]}, {"text": "年", "box": [852, 3041, 924, 3106]}, {"text": "10", "box": [943, 3040, 991, 3070]}, {"text": "16", "box": [1106, 3039, 1153, 3073]}], "linking": [[33, 37]], "id": 37}, {"box": [1433, 3039, 1583, 3114], "text": "签名:", "label": "question", "words": [{"text": "签名", "box": [1433, 3042, 1560, 3114]}, {"text": ":", "box": [1569, 3039, 1583, 3101]}], "linking": [[38, 39]], "id": 38}, {"box": [1600, 3029, 1701, 3099], "text": "王伟", "label": "answer", "words": [{"text": "王伟", "box": [1600, 3029, 1701, 3099]}], "linking": [[38, 39]], "id": 39}]}