{
    "form": [
        {
            "text": "项目",
            "box": [
                373,
                68,
                432,
                90
            ],
            "label": "header"
        },
        {
            "text": "立项",
            "box": [
                437,
                68,
                500,
                90
            ],
            "label": "header"
        },
        {
            "text": "申请",
            "box": [
                506,
                68,
                564,
                90
            ],
            "label": "header"
        },
        {
            "text": "表",
            "box": [
                564,
                68,
                596,
                90
            ],
            "label": "header"
        },
        {
            "text": "项目",
            "box": [
                78,
                117,
                108,
                127
            ],
            "label": "other"
        },
        {
            "text": "名称",
            "box": [
                110,
                117,
                143,
                128
            ],
            "label": "other"
        },
        {
            "text": "2019",
            "box": [
                277,
                118,
                312,
                129
            ],
            "label": "other"
        },
        {
            "text": "年",
            "box": [
                313,
                118,
                328,
                129
            ],
            "label": "other"
        },
        {
            "text": "10",
            "box": [
                330,
                118,
                344,
                129
            ],
            "label": "other"
        },
        {
            "text": "月",
            "box": [
                364,
                118,
                377,
                129
            ],
            "label": "other"
        },
        {
            "text": "5",
            "box": [
                380,
                118,
                386,
                129
            ],
            "label": "other"
        },
        {
            "text": "日",
            "box": [
                410,
                118,
                420,
                129
            ],
            "label": "other"
        },
        {
            "text": "金鹏",
            "box": [
                460,
                117,
                492,
                127
            ],
            "label": "other"
        },
        {
            "text": "项目",
            "box": [
                786,
                119,
                814,
                129
            ],
            "label": "other"
        },
        {
            "text": "背景",
            "box": [
                175,
                154,
                207,
                165
            ],
            "label": "question"
        },
        {
            "text": "介绍",
            "box": [
                208,
                154,
                239,
                165
            ],
            "label": "question"
        },
        {
            "text": "对",
            "box": [
                301,
                161,
                316,
                172
            ],
            "label": "answer"
        },
        {
            "text": "新",
            "box": [
                316,
                161,
                332,
                172
            ],
            "label": "answer"
        },
        {
            "text": "建设",
            "box": [
                333,
                161,
                366,
                172
            ],
            "label": "answer"
        },
        {
            "text": "的",
            "box": [
                368,
                161,
                381,
                172
            ],
            "label": "answer"
        },
        {
            "text": "商业区",
            "box": [
                383,
                161,
                428,
                172
            ],
            "label": "answer"
        },
        {
            "text": "进行",
            "box": [
                430,
                161,
                460,
                172
            ],
            "label": "answer"
        },
        {
            "text": "宣传",
            "box": [
                461,
                161,
                492,
                172
            ],
            "label": "answer"
        },
        {
            "text": "项目",
            "box": [
                175,
                184,
                206,
                196
            ],
            "label": "question"
        },
        {
            "text": "负责",
            "box": [
                208,
                184,
                239,
                197
            ],
            "label": "question"
        },
        {
            "text": "人",
            "box": [
                241,
                185,
                255,
                197
            ],
            "label": "question"
        },
        {
            "text": "(",
            "box": [
                265,
                185,
                270,
                197
            ],
            "label": "question"
        },
        {
            "text": "总",
            "box": [
                272,
                185,
                286,
                198
            ],
            "label": "question"
        },
        {
            "text": "协调",
            "box": [
                288,
                185,
                319,
                198
            ],
            "label": "question"
        },
        {
            "text": "人",
            "box": [
                320,
                186,
                335,
                198
            ],
            "label": "question"
        },
        {
            "text": ")",
            "box": [
                337,
                186,
                343,
                198
            ],
            "label": "question"
        },
        {
            "text": "闫",
            "box": [
                356,
                187,
                370,
                199
            ],
            "label": "answer"
        },
        {
            "text": "克",
            "box": [
                371,
                187,
                387,
                199
            ],
            "label": "answer"
        },
        {
            "text": "义",
            "box": [
                388,
                187,
                402,
                200
            ],
            "label": "answer"
        },
        {
            "text": "职责",
            "box": [
                176,
                203,
                201,
                214
            ],
            "label": "question"
        },
        {
            "text": ":",
            "box": [
                204,
                203,
                206,
                214
            ],
            "label": "question"
        },
        {
            "text": "对",
            "box": [
                215,
                203,
                227,
                214
            ],
            "label": "answer"
        },
        {
            "text": "负责",
            "box": [
                229,
                203,
                254,
                214
            ],
            "label": "answer"
        },
        {
            "text": "团队",
            "box": [
                255,
                203,
                279,
                214
            ],
            "label": "answer"
        },
        {
            "text": "沟通",
            "box": [
                279,
                204,
                304,
                214
            ],
            "label": "answer"
        },
        {
            "text": "协商",
            "box": [
                306,
                204,
                331,
                214
            ],
            "label": "answer"
        },
        {
            "text": "职责",
            "box": [
                332,
                204,
                359,
                214
            ],
            "label": "answer"
        },
        {
            "text": ",",
            "box": [
                361,
                204,
                363,
                214
            ],
            "label": "answer"
        },
        {
            "text": "负责",
            "box": [
                372,
                204,
                397,
                214
            ],
            "label": "answer"
        },
        {
            "text": "汇总",
            "box": [
                399,
                204,
                423,
                214
            ],
            "label": "answer"
        },
        {
            "text": "沟通",
            "box": [
                424,
                204,
                450,
                214
            ],
            "label": "answer"
        },
        {
            "text": "协商",
            "box": [
                450,
                204,
                475,
                214
            ],
            "label": "answer"
        },
        {
            "text": "结果",
            "box": [
                475,
                204,
                500,
                214
            ],
            "label": "answer"
        },
        {
            "text": "及",
            "box": [
                502,
                204,
                514,
                214
            ],
            "label": "answer"
        },
        {
            "text": "项目",
            "box": [
                514,
                204,
                538,
                214
            ],
            "label": "answer"
        },
        {
            "text": "总",
            "box": [
                541,
                204,
                552,
                214
            ],
            "label": "answer"
        },
        {
            "text": "协调",
            "box": [
                554,
                204,
                579,
                215
            ],
            "label": "answer"
        },
        {
            "text": "由",
            "box": [
                640,
                196,
                652,
                207
            ],
            "label": "other"
        },
        {
            "text": "参与",
            "box": [
                654,
                196,
                685,
                208
            ],
            "label": "other"
        },
        {
            "text": "各方",
            "box": [
                686,
                196,
                717,
                208
            ],
            "label": "other"
        },
        {
            "text": "推选",
            "box": [
                717,
                196,
                750,
                208
            ],
            "label": "other"
        },
        {
            "text": "项目",
            "box": [
                175,
                231,
                204,
                242
            ],
            "label": "question"
        },
        {
            "text": "级别",
            "box": [
                208,
                231,
                239,
                242
            ],
            "label": "question"
        },
        {
            "text": "/",
            "box": [
                243,
                231,
                249,
                242
            ],
            "label": "question"
        },
        {
            "text": "类别",
            "box": [
                252,
                231,
                282,
                242
            ],
            "label": "question"
        },
        {
            "text": "广告",
            "box": [
                387,
                232,
                419,
                243
            ],
            "label": "answer"
        },
        {
            "text": "多",
            "box": [
                420,
                232,
                435,
                243
            ],
            "label": "answer"
        },
        {
            "text": "经",
            "box": [
                435,
                232,
                451,
                243
            ],
            "label": "answer"
        },
        {
            "text": "项目",
            "box": [
                78,
                242,
                106,
                253
            ],
            "label": "question"
        },
        {
            "text": "简介",
            "box": [
                110,
                242,
                141,
                253
            ],
            "label": "question"
        },
        {
            "text": "计划",
            "box": [
                175,
                261,
                206,
                273
            ],
            "label": "question"
        },
        {
            "text": "时间",
            "box": [
                208,
                261,
                239,
                273
            ],
            "label": "question"
        },
        {
            "text": "2019",
            "box": [
                431,
                262,
                460,
                273
            ],
            "label": "answer"
        },
        {
            "text": "年",
            "box": [
                460,
                262,
                476,
                273
            ],
            "label": "answer"
        },
        {
            "text": "11",
            "box": [
                478,
                262,
                490,
                273
            ],
            "label": "answer"
        },
        {
            "text": "月",
            "box": [
                491,
                262,
                504,
                273
            ],
            "label": "answer"
        },
        {
            "text": "5",
            "box": [
                508,
                262,
                514,
                273
            ],
            "label": "answer"
        },
        {
            "text": "日",
            "box": [
                516,
                262,
                529,
                273
            ],
            "label": "answer"
        },
        {
            "text": "至",
            "box": [
                531,
                262,
                546,
                273
            ],
            "label": "answer"
        },
        {
            "text": "2020",
            "box": [
                589,
                263,
                618,
                273
            ],
            "label": "answer"
        },
        {
            "text": "年",
            "box": [
                618,
                263,
                634,
                273
            ],
            "label": "answer"
        },
        {
            "text": "5",
            "box": [
                666,
                263,
                674,
                273
            ],
            "label": "answer"
        },
        {
            "text": "月",
            "box": [
                674,
                263,
                687,
                273
            ],
            "label": "answer"
        },
        {
            "text": "9",
            "box": [
                708,
                263,
                716,
                273
            ],
            "label": "answer"
        },
        {
            "text": "日",
            "box": [
                719,
                263,
                730,
                273
            ],
            "label": "answer"
        },
        {
            "text": "项目",
            "box": [
                175,
                295,
                205,
                306
            ],
            "label": "question"
        },
        {
            "text": "实施",
            "box": [
                208,
                295,
                239,
                306
            ],
            "label": "question"
        },
        {
            "text": "办法",
            "box": [
                240,
                295,
                270,
                306
            ],
            "label": "question"
        },
        {
            "text": "、",
            "box": [
                272,
                295,
                276,
                306
            ],
            "label": "question"
        },
        {
            "text": "执行",
            "box": [
                287,
                295,
                318,
                306
            ],
            "label": "question"
        },
        {
            "text": "方案",
            "box": [
                319,
                295,
                351,
                306
            ],
            "label": "question"
        },
        {
            "text": "利用",
            "box": [
                388,
                295,
                418,
                306
            ],
            "label": "answer"
        },
        {
            "text": "各大",
            "box": [
                420,
                295,
                451,
                306
            ],
            "label": "answer"
        },
        {
            "text": "商城",
            "box": [
                452,
                295,
                482,
                307
            ],
            "label": "answer"
        },
        {
            "text": "外",
            "box": [
                483,
                295,
                497,
                307
            ],
            "label": "answer"
        },
        {
            "text": "屏幕",
            "box": [
                499,
                295,
                530,
                307
            ],
            "label": "answer"
        },
        {
            "text": "进行",
            "box": [
                531,
                295,
                562,
                307
            ],
            "label": "answer"
        },
        {
            "text": "视频",
            "box": [
                563,
                296,
                595,
                307
            ],
            "label": "answer"
        },
        {
            "text": "播放",
            "box": [
                595,
                296,
                627,
                307
            ],
            "label": "answer"
        },
        {
            "text": "宣传",
            "box": [
                627,
                296,
                658,
                307
            ],
            "label": "answer"
        },
        {
            "text": "合作",
            "box": [
                173,
                332,
                206,
                344
            ],
            "label": "question"
        },
        {
            "text": "商",
            "box": [
                207,
                332,
                222,
                344
            ],
            "label": "question"
        },
        {
            "text": "介绍",
            "box": [
                223,
                332,
                254,
                344
            ],
            "label": "question"
        },
        {
            "text": "/",
            "box": [
                258,
                332,
                264,
                344
            ],
            "label": "question"
        },
        {
            "text": "资质",
            "box": [
                268,
                332,
                298,
                344
            ],
            "label": "question"
        },
        {
            "text": "等",
            "box": [
                300,
                332,
                314,
                344
            ],
            "label": "question"
        },
        {
            "text": "项目",
            "box": [
                75,
                370,
                105,
                380
            ],
            "label": "question"
        },
        {
            "text": "需求",
            "box": [
                108,
                370,
                139,
                381
            ],
            "label": "question"
        },
        {
            "text": "需要",
            "box": [
                362,
                371,
                394,
                382
            ],
            "label": "answer"
        },
        {
            "text": "各大",
            "box": [
                394,
                371,
                426,
                382
            ],
            "label": "answer"
        },
        {
            "text": "商城",
            "box": [
                426,
                371,
                458,
                382
            ],
            "label": "answer"
        },
        {
            "text": "商户",
            "box": [
                458,
                371,
                488,
                382
            ],
            "label": "answer"
        },
        {
            "text": "配合",
            "box": [
                490,
                371,
                521,
                382
            ],
            "label": "answer"
        },
        {
            "text": "宣传",
            "box": [
                522,
                371,
                554,
                382
            ],
            "label": "answer"
        },
        {
            "text": "负责",
            "box": [
                183,
                400,
                213,
                410
            ],
            "label": "question"
        },
        {
            "text": "人",
            "box": [
                214,
                400,
                229,
                410
            ],
            "label": "question"
        },
        {
            "text": "王贵福",
            "box": [
                258,
                402,
                306,
                413
            ],
            "label": "answer"
        },
        {
            "text": "任务",
            "box": [
                377,
                400,
                406,
                411
            ],
            "label": "question"
        },
        {
            "text": "策划",
            "box": [
                458,
                403,
                488,
                414
            ],
            "label": "answer"
        },
        {
            "text": "姓名",
            "box": [
                564,
                401,
                595,
                412
            ],
            "label": "question"
        },
        {
            "text": "任重",
            "box": [
                632,
                405,
                663,
                415
            ],
            "label": "answer"
        },
        {
            "text": "任务",
            "box": [
                731,
                401,
                762,
                412
            ],
            "label": "question"
        },
        {
            "text": "合作",
            "box": [
                810,
                405,
                842,
                417
            ],
            "label": "answer"
        },
        {
            "text": "沟通",
            "box": [
                844,
                405,
                873,
                416
            ],
            "label": "answer"
        },
        {
            "text": "人员",
            "box": [
                75,
                420,
                106,
                430
            ],
            "label": "question"
        },
        {
            "text": "分工",
            "box": [
                107,
                420,
                139,
                430
            ],
            "label": "question"
        },
        {
            "text": "姓名",
            "box": [
                189,
                420,
                220,
                431
            ],
            "label": "question"
        },
        {
            "text": "王",
            "box": [
                264,
                421,
                280,
                431
            ],
            "label": "answer"
        },
        {
            "text": "影",
            "box": [
                281,
                420,
                296,
                430
            ],
            "label": "answer"
        },
        {
            "text": "任务",
            "box": [
                376,
                420,
                407,
                431
            ],
            "label": "question"
        },
        {
            "text": "监督",
            "box": [
                459,
                426,
                490,
                436
            ],
            "label": "answer"
        },
        {
            "text": "姓名",
            "box": [
                563,
                421,
                595,
                432
            ],
            "label": "question"
        },
        {
            "text": "武",
            "box": [
                636,
                423,
                650,
                433
            ],
            "label": "answer"
        },
        {
            "text": "强",
            "box": [
                652,
                423,
                666,
                433
            ],
            "label": "answer"
        },
        {
            "text": "任务",
            "box": [
                731,
                421,
                762,
                432
            ],
            "label": "question"
        },
        {
            "text": "支出",
            "box": [
                814,
                425,
                845,
                437
            ],
            "label": "answer"
        },
        {
            "text": "管理",
            "box": [
                847,
                425,
                876,
                437
            ],
            "label": "answer"
        },
        {
            "text": "姓名",
            "box": [
                189,
                440,
                220,
                452
            ],
            "label": "other"
        },
        {
            "text": "任务",
            "box": [
                376,
                441,
                406,
                452
            ],
            "label": "other"
        },
        {
            "text": "姓名",
            "box": [
                563,
                441,
                595,
                452
            ],
            "label": "other"
        },
        {
            "text": "任务",
            "box": [
                731,
                442,
                762,
                453
            ],
            "label": "other"
        },
        {
            "text": "实施",
            "box": [
                59,
                471,
                90,
                482
            ],
            "label": "question"
        },
        {
            "text": "内容",
            "box": [
                93,
                471,
                122,
                482
            ],
            "label": "question"
        },
        {
            "text": "商业",
            "box": [
                164,
                474,
                196,
                485
            ],
            "label": "answer"
        },
        {
            "text": "宣传",
            "box": [
                195,
                474,
                229,
                486
            ],
            "label": "answer"
        },
        {
            "text": "达标",
            "box": [
                320,
                472,
                352,
                482
            ],
            "label": "question"
        },
        {
            "text": "要求",
            "box": [
                353,
                472,
                385,
                482
            ],
            "label": "question"
        },
        {
            "text": "宣传",
            "box": [
                450,
                475,
                481,
                487
            ],
            "label": "answer"
        },
        {
            "text": "时间",
            "box": [
                482,
                475,
                512,
                487
            ],
            "label": "answer"
        },
        {
            "text": "满",
            "box": [
                514,
                475,
                529,
                487
            ],
            "label": "answer"
        },
        {
            "text": "一个月",
            "box": [
                531,
                475,
                575,
                487
            ],
            "label": "answer"
        },
        {
            "text": "时间",
            "box": [
                625,
                473,
                656,
                484
            ],
            "label": "question"
        },
        {
            "text": "要求",
            "box": [
                657,
                473,
                687,
                484
            ],
            "label": "question"
        },
        {
            "text": "2020",
            "box": [
                731,
                473,
                760,
                484
            ],
            "label": "answer"
        },
        {
            "text": "年",
            "box": [
                761,
                473,
                777,
                484
            ],
            "label": "answer"
        },
        {
            "text": "1",
            "box": [
                779,
                473,
                783,
                484
            ],
            "label": "answer"
        },
        {
            "text": "月",
            "box": [
                784,
                473,
                797,
                484
            ],
            "label": "answer"
        },
        {
            "text": "5",
            "box": [
                801,
                473,
                807,
                484
            ],
            "label": "answer"
        },
        {
            "text": "日",
            "box": [
                810,
                473,
                821,
                484
            ],
            "label": "answer"
        },
        {
            "text": ",",
            "box": [
                825,
                473,
                829,
                484
            ],
            "label": "answer"
        },
        {
            "text": "2020",
            "box": [
                840,
                473,
                869,
                484
            ],
            "label": "answer"
        },
        {
            "text": "年",
            "box": [
                870,
                473,
                883,
                484
            ],
            "label": "answer"
        },
        {
            "text": "2",
            "box": [
                884,
                473,
                890,
                484
            ],
            "label": "answer"
        },
        {
            "text": "月",
            "box": [
                891,
                473,
                904,
                484
            ],
            "label": "answer"
        },
        {
            "text": "5",
            "box": [
                908,
                473,
                914,
                484
            ],
            "label": "answer"
        },
        {
            "text": "日",
            "box": [
                915,
                473,
                927,
                484
            ],
            "label": "answer"
        },
        {
            "text": "实施",
            "box": [
                58,
                511,
                90,
                523
            ],
            "label": "other"
        },
        {
            "text": "内容",
            "box": [
                91,
                511,
                122,
                523
            ],
            "label": "other"
        },
        {
            "text": "达标",
            "box": [
                319,
                512,
                352,
                523
            ],
            "label": "other"
        },
        {
            "text": "要求",
            "box": [
                352,
                512,
                383,
                522
            ],
            "label": "other"
        },
        {
            "text": "时间",
            "box": [
                625,
                513,
                656,
                524
            ],
            "label": "question"
        },
        {
            "text": "要求",
            "box": [
                655,
                513,
                688,
                524
            ],
            "label": "question"
        },
        {
            "text": "开始",
            "box": [
                747,
                513,
                779,
                524
            ],
            "label": "answer"
        },
        {
            "text": "时间",
            "box": [
                780,
                513,
                810,
                524
            ],
            "label": "answer"
        },
        {
            "text": "、",
            "box": [
                812,
                513,
                817,
                524
            ],
            "label": "answer"
        },
        {
            "text": "结束",
            "box": [
                827,
                513,
                859,
                525
            ],
            "label": "answer"
        },
        {
            "text": "时间",
            "box": [
                860,
                513,
                889,
                525
            ],
            "label": "answer"
        },
        {
            "text": "实施",
            "box": [
                58,
                550,
                89,
                561
            ],
            "label": "other"
        },
        {
            "text": "内容",
            "box": [
                91,
                550,
                122,
                561
            ],
            "label": "other"
        },
        {
            "text": "达标",
            "box": [
                319,
                550,
                352,
                561
            ],
            "label": "other"
        },
        {
            "text": "要求",
            "box": [
                353,
                550,
                384,
                561
            ],
            "label": "other"
        },
        {
            "text": "时间",
            "box": [
                625,
                551,
                655,
                562
            ],
            "label": "question"
        },
        {
            "text": "要求",
            "box": [
                656,
                551,
                687,
                562
            ],
            "label": "question"
        },
        {
            "text": "开始",
            "box": [
                747,
                551,
                779,
                563
            ],
            "label": "answer"
        },
        {
            "text": "时间",
            "box": [
                780,
                551,
                811,
                563
            ],
            "label": "answer"
        },
        {
            "text": "、",
            "box": [
                813,
                552,
                817,
                563
            ],
            "label": "answer"
        },
        {
            "text": "结束",
            "box": [
                827,
                552,
                859,
                563
            ],
            "label": "answer"
        },
        {
            "text": "时间",
            "box": [
                861,
                552,
                889,
                563
            ],
            "label": "answer"
        },
        {
            "text": "预期",
            "box": [
                54,
                599,
                85,
                610
            ],
            "label": "question"
        },
        {
            "text": "完成",
            "box": [
                87,
                599,
                118,
                610
            ],
            "label": "question"
        },
        {
            "text": "目标",
            "box": [
                122,
                599,
                150,
                610
            ],
            "label": "question"
        },
        {
            "text": "(",
            "box": [
                63,
                618,
                68,
                629
            ],
            "label": "question"
        },
        {
            "text": "达成",
            "box": [
                70,
                618,
                102,
                629
            ],
            "label": "question"
        },
        {
            "text": "效果",
            "box": [
                102,
                618,
                134,
                629
            ],
            "label": "question"
        },
        {
            "text": ")",
            "box": [
                136,
                618,
                141,
                629
            ],
            "label": "question"
        },
        {
            "text": "使",
            "box": [
                458,
                610,
                473,
                621
            ],
            "label": "answer"
        },
        {
            "text": "新建",
            "box": [
                474,
                610,
                506,
                621
            ],
            "label": "answer"
        },
        {
            "text": "商业区",
            "box": [
                506,
                610,
                554,
                622
            ],
            "label": "answer"
        },
        {
            "text": "日",
            "box": [
                558,
                610,
                568,
                622
            ],
            "label": "answer"
        },
        {
            "text": "收益",
            "box": [
                571,
                610,
                602,
                622
            ],
            "label": "answer"
        },
        {
            "text": "达",
            "box": [
                603,
                610,
                618,
                622
            ],
            "label": "answer"
        },
        {
            "text": "200",
            "box": [
                619,
                610,
                640,
                622
            ],
            "label": "answer"
        },
        {
            "text": "万",
            "box": [
                641,
                610,
                656,
                622
            ],
            "label": "answer"
        },
        {
            "text": ",",
            "box": [
                659,
                610,
                662,
                622
            ],
            "label": "answer"
        },
        {
            "text": "成为",
            "box": [
                672,
                610,
                704,
                622
            ],
            "label": "answer"
        },
        {
            "text": "城市",
            "box": [
                704,
                610,
                735,
                622
            ],
            "label": "answer"
        },
        {
            "text": "主要",
            "box": [
                737,
                610,
                768,
                622
            ],
            "label": "answer"
        },
        {
            "text": "经济",
            "box": [
                768,
                611,
                800,
                622
            ],
            "label": "answer"
        },
        {
            "text": "区域",
            "box": [
                802,
                611,
                833,
                622
            ],
            "label": "answer"
        },
        {
            "text": "项目",
            "box": [
                52,
                684,
                82,
                695
            ],
            "label": "question"
        },
        {
            "text": "审批",
            "box": [
                86,
                684,
                117,
                695
            ],
            "label": "question"
        },
        {
            "text": "意见",
            "box": [
                117,
                684,
                149,
                695
            ],
            "label": "question"
        },
        {
            "text": "予以",
            "box": [
                460,
                680,
                491,
                690
            ],
            "label": "answer"
        },
        {
            "text": "通过",
            "box": [
                492,
                680,
                524,
                690
            ],
            "label": "answer"
        },
        {
            "text": "否",
            "box": [
                395,
                733,
                415,
                742
            ],
            "label": "other"
        },
        {
            "text": "项目",
            "box": [
                72,
                765,
                101,
                776
            ],
            "label": "question"
        },
        {
            "text": "补充",
            "box": [
                104,
                765,
                135,
                776
            ],
            "label": "question"
        },
        {
            "text": "项目",
            "box": [
                390,
                766,
                419,
                777
            ],
            "label": "answer"
        },
        {
            "text": "出现",
            "box": [
                423,
                766,
                453,
                777
            ],
            "label": "answer"
        },
        {
            "text": "超时",
            "box": [
                454,
                766,
                484,
                777
            ],
            "label": "answer"
        },
        {
            "text": "/",
            "box": [
                490,
                766,
                495,
                777
            ],
            "label": "answer"
        },
        {
            "text": "特殊",
            "box": [
                499,
                766,
                531,
                777
            ],
            "label": "answer"
        },
        {
            "text": "情况",
            "box": [
                532,
                766,
                563,
                777
            ],
            "label": "answer"
        },
        {
            "text": "需",
            "box": [
                564,
                766,
                580,
                777
            ],
            "label": "answer"
        },
        {
            "text": "补充",
            "box": [
                581,
                766,
                612,
                777
            ],
            "label": "answer"
        },
        {
            "text": "清晰",
            "box": [
                612,
                766,
                644,
                777
            ],
            "label": "answer"
        },
        {
            "text": "说明",
            "box": [
                645,
                766,
                675,
                777
            ],
            "label": "answer"
        },
        {
            "text": "沟通",
            "box": [
                52,
                816,
                83,
                827
            ],
            "label": "question"
        },
        {
            "text": "结果",
            "box": [
                83,
                816,
                116,
                827
            ],
            "label": "question"
        },
        {
            "text": "记录",
            "box": [
                116,
                816,
                147,
                827
            ],
            "label": "question"
        },
        {
            "text": "沟通",
            "box": [
                381,
                817,
                412,
                828
            ],
            "label": "answer"
        },
        {
            "text": "会议",
            "box": [
                413,
                817,
                443,
                828
            ],
            "label": "answer"
        },
        {
            "text": "记录",
            "box": [
                445,
                817,
                476,
                828
            ],
            "label": "answer"
        },
        {
            "text": "(",
            "box": [
                485,
                817,
                491,
                828
            ],
            "label": "answer"
        },
        {
            "text": "文字",
            "box": [
                492,
                817,
                524,
                828
            ],
            "label": "answer"
        },
        {
            "text": "介绍",
            "box": [
                525,
                817,
                557,
                828
            ],
            "label": "answer"
        },
        {
            "text": "/",
            "box": [
                567,
                817,
                574,
                828
            ],
            "label": "answer"
        },
        {
            "text": "文件",
            "box": [
                577,
                817,
                608,
                828
            ],
            "label": "answer"
        },
        {
            "text": "附件",
            "box": [
                610,
                817,
                640,
                828
            ],
            "label": "answer"
        },
        {
            "text": "形式",
            "box": [
                643,
                818,
                672,
                829
            ],
            "label": "answer"
        },
        {
            "text": ")",
            "box": [
                673,
                818,
                679,
                829
            ],
            "label": "answer"
        },
        {
            "text": "项目",
            "box": [
                51,
                877,
                80,
                888
            ],
            "label": "question"
        },
        {
            "text": "完结",
            "box": [
                83,
                877,
                114,
                888
            ],
            "label": "question"
        },
        {
            "text": "效果",
            "box": [
                116,
                877,
                146,
                888
            ],
            "label": "question"
        },
        {
            "text": "针对",
            "box": [
                429,
                878,
                459,
                889
            ],
            "label": "answer"
        },
        {
            "text": "项目",
            "box": [
                460,
                878,
                489,
                889
            ],
            "label": "answer"
        },
        {
            "text": "实施",
            "box": [
                493,
                878,
                524,
                889
            ],
            "label": "answer"
        },
        {
            "text": "效果",
            "box": [
                525,
                878,
                556,
                889
            ],
            "label": "answer"
        },
        {
            "text": "作",
            "box": [
                557,
                878,
                572,
                889
            ],
            "label": "answer"
        },
        {
            "text": "总结",
            "box": [
                573,
                878,
                605,
                889
            ],
            "label": "answer"
        },
        {
            "text": "说明",
            "box": [
                605,
                879,
                636,
                890
            ],
            "label": "answer"
        }
    ]
}